{
  "type": "Feature",
  "properties": {
    "iso:country":"JP",
    "sg:address":"Shibuya Tokyu Property Bldg.1501 1-32-12 Higashi, Shibuya-ku",
    "sg:city":"Tokyo",
    "sg:classifiers":[
        {
            "category":"Professional",
            "subcategory":"Advertising",
            "type":"Services"
        }
    ],
    "sg:postcode":"150-0011",
    "sg:tags":[
        "online-marketing",
        "ad-network",
        "banner",
        "advertising",
        "japan",
        "tokyo",
        "planning",
        "meetings",
        "events",
        "campaigns"
    ],
    "sg:website":"http://agilemedia.jp/en/about/",
    "wof:name":"Agile Media Network",
    "wof:placetype":"venue"
},
  "geometry": {"coordinates":[139.70929760000001,35.6542145],"type":"Point"}
}