{
  "type": "Feature",
  "properties": {
    "iso:country":"JP",
    "sg:address":"Riverside Seven Bldf. 3F Sotokanda 2-7-9, Chiyoda-ku",
    "sg:city":"Tokyo",
    "sg:classifiers":[
        {
            "category":"Manufacturing",
            "subcategory":"Electronics",
            "type":"Manufacturing & Wholesale Goods"
        }
    ],
    "sg:postcode":"101- 0021",
    "sg:tags":[
        "digital-camera",
        "cerevo-cam",
        "cerevo-life",
        "photo-management",
        "photo-sharing",
        "3g",
        "wifi"
    ],
    "sg:website":"http://cerevo.com/",
    "wof:name":"Cerevo",
    "wof:placetype":"venue"
},
  "geometry": {"coordinates":[139.76970499999999,35.7019106],"type":"Point"}
}