{
  "type": "Feature",
  "properties": {
    "iso:country":"JP",
    "sg:address":"5-80 Kanagawa Chusho Kigyo Center Building, Suite 7F",
    "sg:city":"5 Yokohama City, Kanagawa",
    "sg:classifiers":[
        {
            "category":"Professional",
            "subcategory":"Computer Services",
            "type":"Services"
        }
    ],
    "sg:postcode":"231-0015",
    "sg:tags":[
        "dango",
        "meromero-park",
        "japan",
        "social-gaming"
    ],
    "sg:website":"http://dango-net.com/",
    "wof:name":"dango",
    "wof:placetype":"venue"
},
  "geometry": {"coordinates":[139.633748,35.4470518],"type":"Point"}
}